itsdangerous-stubs/METADATA.toml
itsdangerous-stubs/__init__.pyi
types_itsdangerous-1.1.5.dist-info/METADATA
types_itsdangerous-1.1.5.dist-info/WHEEL
types_itsdangerous-1.1.5.dist-info/top_level.txt
types_itsdangerous-1.1.5.dist-info/RECORD
