Metadata-Version: 2.1
Name: types-itsdangerous
Version: 1.1.5
Summary: Typing stubs for itsdangerous
Home-page: https://github.com/python/typeshed
License: Apache-2.0 license
Platform: UNKNOWN
Classifier: License :: OSI Approved :: Apache Software License
Classifier: Typing :: Typed
